pytoda/__init__.py
pytoda/data_splitter.py
pytoda/files.py
pytoda/transforms.py
pytoda/types.py
pytoda/warnings.py
pytoda/datasets/__init__.py
pytoda/datasets/_cache_datasource.py
pytoda/datasets/_csv_eager_dataset.py
pytoda/datasets/_csv_lazy_dataset.py
pytoda/datasets/_csv_statistics.py
pytoda/datasets/_fasta_eager_dataset.py
pytoda/datasets/_fasta_lazy_dataset.py
pytoda/datasets/_smi_eager_dataset.py
pytoda/datasets/_smi_lazy_dataset.py
pytoda/datasets/_table_dataset.py
pytoda/datasets/annotated_dataset.py
pytoda/datasets/base_dataset.py
pytoda/datasets/dataframe_dataset.py
pytoda/datasets/distributional_dataset.py
pytoda/datasets/drug_affinity_dataset.py
pytoda/datasets/drug_sensitivity_dataset.py
pytoda/datasets/drug_sensitivity_dose_dataset.py
pytoda/datasets/gene_expression_dataset.py
pytoda/datasets/polymer_dataset.py
pytoda/datasets/protein_protein_interaction_dataset.py
pytoda/datasets/protein_sequence_dataset.py
pytoda/datasets/set_matching_dataset.py
pytoda/datasets/smiles_dataset.py
pytoda/datasets/tests/__init__.py
pytoda/datasets/tests/test_annotated_dataset.py
pytoda/datasets/tests/test_base_dataset.py
pytoda/datasets/tests/test_distributional_dataset.py
pytoda/datasets/tests/test_drug_affinity_dataset.py
pytoda/datasets/tests/test_drug_sensitivity_dataset.py
pytoda/datasets/tests/test_drug_sensitivity_dose_dataset.py
pytoda/datasets/tests/test_gene_expression_dataset.py
pytoda/datasets/tests/test_polymer_dataset.py
pytoda/datasets/tests/test_protein_protein_interaction_dataset.py
pytoda/datasets/tests/test_protein_sequence_dataset.py
pytoda/datasets/tests/test_set_matching_dataset.py
pytoda/datasets/tests/test_smiles_datasets.py
pytoda/datasets/utils/__init__.py
pytoda/datasets/utils/background_tensors.py
pytoda/datasets/utils/factories.py
pytoda/datasets/utils/utils.py
pytoda/datasets/utils/wrappers.py
pytoda/preprocessing/__init__.py
pytoda/preprocessing/crawlers.py
pytoda/preprocessing/smi.py
pytoda/preprocessing/tests/__init__.py
pytoda-1.1.7.dist-info/licenses/LICENSE
pytoda-1.1.7.dist-info/METADATA
pytoda-1.1.7.dist-info/WHEEL
pytoda-1.1.7.dist-info/top_level.txt
pytoda-1.1.7.dist-info/RECORD
