Metadata-Version: 2.4
Name: pytoda
Version: 1.1.7
Summary: pytoda: PaccMann PyTorch Dataset Classes.
Home-page: https://github.com/PaccMann/paccmann_datasets
Author: Matteo Manica, Jannis Born, Joris Cadow
Author-email: drugilsberg@gmail.com, jannis.born@gmx.de, joriscadow@gmail.com
License: MIT
Classifier: Intended Audience :: Developers
Classifier: Intended Audience :: Science/Research
Classifier: License :: OSI Approved :: MIT License
Classifier: Programming Language :: Python :: 3
Classifier: Programming Language :: Python :: 3.7
Classifier: Programming Language :: Python :: 3.8
Classifier: Programming Language :: Python :: 3.9
Classifier: Programming Language :: Python :: 3.10
Classifier: Programming Language :: Python :: 3.11
Classifier: Programming Language :: Python :: 3.12
Classifier: Topic :: Software Development :: Libraries :: Python Modules
License-File: LICENSE
Requires-Dist: numpy
Requires-Dist: scikit-learn
Requires-Dist: pandas
Requires-Dist: torch>=1.4.0
Requires-Dist: diskcache
Requires-Dist: dill>=0.3.3
Requires-Dist: selfies>=2.1.1
Requires-Dist: upfp
Requires-Dist: SmilesPE>=0.0.3
Requires-Dist: pyfaidx
Requires-Dist: pubchempy
Requires-Dist: importlib_resources
Requires-Dist: Unidecode
Requires-Dist: rdkit
Dynamic: author
Dynamic: author-email
Dynamic: classifier
Dynamic: description
Dynamic: description-content-type
Dynamic: home-page
Dynamic: license
Dynamic: license-file
Dynamic: requires-dist
Dynamic: summary
